django_edge_isr-0.0.8.dist-info/licenses/LICENSE
edge_isr/__init__.py
edge_isr/context.py
edge_isr/decorators.py
edge_isr/graph.py
edge_isr/middleware.py
edge_isr/policy.py
edge_isr/settings.py
edge_isr/tags.py
edge_isr/utils.py
edge_isr/admin/__init__.py
edge_isr/admin/urls.py
edge_isr/admin/views.py
edge_isr/connectors/__init__.py
edge_isr/connectors/base.py
edge_isr/connectors/cloudflare.py
edge_isr/connectors/cloudfront.py
edge_isr/management/__init__.py
edge_isr/management/commands/__init__.py
edge_isr/management/commands/revalidate_tags.py
edge_isr/management/commands/warm_url.py
edge_isr/revalidate/__init__.py
edge_isr/revalidate/queue.py
edge_isr/revalidate/tasks.py
django_edge_isr-0.0.8.dist-info/METADATA
django_edge_isr-0.0.8.dist-info/WHEEL
django_edge_isr-0.0.8.dist-info/top_level.txt
django_edge_isr-0.0.8.dist-info/RECORD
