Metadata-Version: 2.4
Name: django-edge-isr
Version: 0.0.8
Summary: Incremental Static Revalidation for Django (SWR + tag-based invalidation + warmup + CDN connectors).
Author-email: Barhamou ISSAKA HAMA <hamabarhamou@gmail.com>
Maintainer-email: Barhamou ISSAKA HAMA <hamabarhamou@gmail.com>
License: MIT
Project-URL: Homepage, https://hamabarhamou.github.io/django-edge-isr/
Project-URL: Documentation, https://hamabarhamou.github.io/django-edge-isr/
Project-URL: Repository, https://github.com/HamaBarhamou/django-edge-isr
Project-URL: Issues, https://github.com/HamaBarhamou/django-edge-isr/issues
Project-URL: Changelog, https://hamabarhamou.github.io/django-edge-isr/changelog/
Project-URL: Author – GitHub, https://github.com/HamaBarhamou
Project-URL: Author – LinkedIn, https://www.linkedin.com/in/barhamou-issaka-hama-90047b179/
Classifier: Framework :: Django
Classifier: Framework :: Django :: 4.2
Classifier: Framework :: Django :: 5
Classifier: Programming Language :: Python :: 3
Classifier: License :: OSI Approved :: MIT License
Classifier: Operating System :: OS Independent
Requires-Python: >=3.10
License-File: LICENSE
Requires-Dist: Django>=4.2
Requires-Dist: redis>=5.0.0
Requires-Dist: requests>=2.31.0
Requires-Dist: typing-extensions>=4.7.0
Provides-Extra: celery
Requires-Dist: celery>=5.3; extra == "celery"
Provides-Extra: rq
Requires-Dist: rq>=1.15; extra == "rq"
Requires-Dist: redis>=5.0.0; extra == "rq"
Provides-Extra: cloudfront
Requires-Dist: boto3>=1.26; extra == "cloudfront"
Provides-Extra: dev
Requires-Dist: pytest>=7.4; extra == "dev"
Requires-Dist: pytest-django>=4.7; extra == "dev"
Requires-Dist: ruff>=0.4.0; extra == "dev"
Requires-Dist: black>=24.4.0; extra == "dev"
Requires-Dist: fakeredis>=2.22.0; extra == "dev"
Dynamic: license-file
